LICENSE
MANIFEST.in
README.md
requirements.txt
setup.py
gpt_pilot.egg-info/PKG-INFO
gpt_pilot.egg-info/SOURCES.txt
gpt_pilot.egg-info/dependency_links.txt
gpt_pilot.egg-info/requires.txt
gpt_pilot.egg-info/top_level.txt
pilot/__init__.py
pilot/db_init.py
pilot/instructions.comment.py
pilot/main.py
pilot/test_main_e2e.py
pilot/const/code_execution.py
pilot/const/common.py
pilot/const/function_calls.py
pilot/const/ipc.py
pilot/const/llm.py
pilot/const/messages.py
pilot/const/telemetry.py
pilot/database/__init__.py
pilot/database/config.py
pilot/database/database.py
pilot/database/models/__init__.py
pilot/database/models/app.py
pilot/database/models/architecture.py
pilot/database/models/command_runs.py
pilot/database/models/development.py
pilot/database/models/development_planning.py
pilot/database/models/development_steps.py
pilot/database/models/environment_setup.py
pilot/database/models/feature.py
pilot/database/models/file_snapshot.py
pilot/database/models/files.py
pilot/database/models/project_description.py
pilot/database/models/user.py
pilot/database/models/user_apps.py
pilot/database/models/user_inputs.py
pilot/database/models/user_stories.py
pilot/database/models/user_tasks.py
pilot/database/models/components/__init__.py
pilot/database/models/components/base_models.py
pilot/database/models/components/progress_step.py
pilot/database/models/components/sqlite_middlewares.py
pilot/helpers/Agent.py
pilot/helpers/AgentConvo.py
pilot/helpers/Debugger.py
pilot/helpers/Project.py
pilot/helpers/__init__.py
pilot/helpers/cli.py
pilot/helpers/files.py
pilot/helpers/ipc.py
pilot/helpers/test_AgentConvo.py
pilot/helpers/test_Debugger.py
pilot/helpers/test_Project.py
pilot/helpers/test_cli.py
pilot/helpers/agents/Architect.py
pilot/helpers/agents/CodeMonkey.py
pilot/helpers/agents/Developer.py
pilot/helpers/agents/ProductOwner.py
pilot/helpers/agents/TechLead.py
pilot/helpers/agents/TechnicalWriter.py
pilot/helpers/agents/__init__.py
pilot/helpers/agents/test_CodeMonkey.py
pilot/helpers/agents/test_Developer.py
pilot/helpers/agents/test_ProductOwner.py
pilot/helpers/agents/test_TechLead.py
