Metadata-Version: 2.1
Name: gpt-pilot
Version: 0.0.10
Summary: GPT Pilot - an AI developer that works with you to build complex projects
Home-page: https://www.pythagora.ai
Author-email: info@pythagora.ai
License: MIT
Classifier: Development Status :: 3 - Alpha
Classifier: Intended Audience :: Developers
Classifier: License :: OSI Approved :: MIT License
Classifier: Programming Language :: Python :: 3
Requires-Python: >=3.9
License-File: LICENSE
